mimebytes/__init__.py
mimebytes/_version.py
mimebytes/base.py
mimebytes/image.py
mimebytes/mime.py
mimebytes-0.2.0.dist-info/LICENSE
mimebytes-0.2.0.dist-info/METADATA
mimebytes-0.2.0.dist-info/WHEEL
mimebytes-0.2.0.dist-info/top_level.txt
mimebytes-0.2.0.dist-info/RECORD
