Metadata-Version: 2.1
Name: mimebytes
Version: 0.2.0
Summary: Make repr of bytes better in IPython
Author-email: Bane Sullivan <hello@banesullivan.com>
Project-URL: Bug Tracker, https://github.com/banesullivan/mimebytes/issues
Project-URL: Source Code, https://github.com/banesullivan/mimebytes
Classifier: Development Status :: 4 - Beta
Classifier: License :: OSI Approved :: MIT License
Classifier: Intended Audience :: Science/Research
Classifier: Topic :: Scientific/Engineering :: Information Analysis
Classifier: Operating System :: OS Independent
Classifier: Programming Language :: Python :: 3.8
Classifier: Programming Language :: Python :: 3.9
Classifier: Programming Language :: Python :: 3.10
Classifier: Programming Language :: Python :: 3.11
Classifier: Programming Language :: Python :: 3.12
Requires-Python: >=3.8
License-File: LICENSE
Provides-Extra: magic
Requires-Dist: python-magic ; extra == 'magic'
